libactivation/__init__.py
libactivation/gompertz.py
libactivation/logistic.py
libactivation/logit.py
libactivation/relu.py
libactivation-0.4.0.dist-info/METADATA
libactivation-0.4.0.dist-info/WHEEL
libactivation-0.4.0.dist-info/top_level.txt
libactivation-0.4.0.dist-info/RECORD
