Metadata-Version: 2.1
Name: libactivation
Version: 0.4.0
Author: Bastiaan Quast
Author-email: <bquast@gmail.com>
Keywords: sigmoid,ReLU
Classifier: Development Status :: 3 - Alpha
Classifier: Intended Audience :: Education
Classifier: Programming Language :: Python :: 2
Classifier: Programming Language :: Python :: 3
Classifier: Operating System :: MacOS :: MacOS X
Classifier: Operating System :: Microsoft :: Windows
Requires-Dist: numpy
